{
	"Changes": [
		// Year 1
		{
			"Action": "EditData",
			"Target": "Data/Festivals/winter8",
			"TextOperations": [
				// Set-up
				{
					"Operation": "Append",
					"Target": [
						"Entries",
						"Set-Up_additionalCharacters"
					],
					"Value": "DialaSBV 48 22 right/DeryaSBV 49 22 left/EliasSBV 74 30 down/MaiaSBV 48 25 right/AminaSBV 50 25 left/JumanaSBV 49 24 down/LyenneSBV 87 20 right/BlakeSBV 89 20 left/OpheliaSBV 88 19 down/MiyoungSBV 53 54 right/SilasSBV 54 54 left/ImanSBV 96 26 right/EzraSBV 97 26 left/AriSBV 54 33 up",
					"Delimiter": "/",
				},
				// Main Event
				{
					"Operation": "Append",
					"Target": [
						"Entries",
						"Main-Event_additionalCharacters"
					],
					"Value": "DialaSBV 48 22 right/DeryaSBV 49 22 left/EliasSBV 74 30 down/MaiaSBV 48 25 right/AminaSBV 50 25 left/JumanaSBV 49 24 down/LyenneSBV 87 20 right/BlakeSBV 89 20 left/OpheliaSBV 88 19 down/MiyoungSBV 53 54 right/SilasSBV 54 54 left/ImanSBV 96 26 right/EzraSBV 97 26 left/AriSBV 54 33 up",
					"Delimiter": "/",
				},
			]
		},
		// Year 2
		{
			"Action": "EditData",
			"Target": "Data/Festivals/winter8",
			"TextOperations": [
				// Set-up
				{
					"Operation": "Append",
					"Target": [
						"Entries",
						"Set-Up_additionalCharacters_y2"
					],
					"Value": "DialaSBV 48 22 right/DeryaSBV 49 22 left/EliasSBV 74 30 down/MaiaSBV 48 25 right/AminaSBV 50 25 left/JumanaSBV 49 24 down/LyenneSBV 87 20 right/BlakeSBV 89 20 left/OpheliaSBV 88 19 down/MiyoungSBV 53 54 right/SilasSBV 54 54 left/ImanSBV 96 26 right/EzraSBV 97 26 left/AriSBV 54 33 right",
					"Delimiter": "/",
				},
				// Main Event
				{
					"Operation": "Append",
					"Target": [
						"Entries",
						"Main-Event_additionalCharacters_y2"
					],
					"Value": "DialaSBV 48 22 right/DeryaSBV 49 22 left/EliasSBV 74 30 down/MaiaSBV 48 25 right/AminaSBV 50 25 left/JumanaSBV 49 24 down/LyenneSBV 87 20 right/BlakeSBV 89 20 left/OpheliaSBV 88 19 down/MiyoungSBV 53 54 right/SilasSBV 54 54 left/ImanSBV 96 26 right/EzraSBV 97 26 left/AriSBV 54 33 right",
					"Delimiter": "/",
				},
			]
		},
		// Moon Year 1
		{
			"Action": "EditData",
			"Target": "Data/Festivals/winter8",
			"When": {
				"HasSeenEvent": "skellady.SBVCP_20031402"
			},
			"TextOperations": [
				// Set-up
				{
					"Operation": "Append",
					"Target": [
						"Entries",
						"Set-Up_additionalCharacters"
					],
					"Value": "MoonSBV 78 9 down",
					"Delimiter": "/",
				},
				// Main Event
				{
					"Operation": "Append",
					"Target": [
						"Entries",
						"Main-Event_additionalCharacters"
					],
					"Value": "MoonSBV 78 9 down",
					"Delimiter": "/",
				},
			]
		},
		// Moon Year 2
		{
			"Action": "EditData",
			"Target": "Data/Festivals/winter8",
			"When": {
				"HasSeenEvent": "skellady.SBVCP_20031402"
			},
			"TextOperations": [
				// Set-up
				{
					"Operation": "Append",
					"Target": [
						"Entries",
						"Set-Up_additionalCharacters_y2"
					],
					"Value": "MoonSBV 62 10 down",
					"Delimiter": "/",
				},
				// Main Event
				{
					"Operation": "Append",
					"Target": [
						"Entries",
						"Main-Event_additionalCharacters_y2"
					],
					"Value": "MoonSBV 62 10 down",
					"Delimiter": "/",
				},
			]
		},
		// Demons Year 1
		{
			"Action": "EditData",
			"Target": "Data/Festivals/winter8",
			"When": {
				"HasSeenEvent": "{{ModId}}_20031427"
			},
			"TextOperations": [
				// Set-up
				{
					"Operation": "Append",
					"Target": [
						"Entries",
						"Set-Up_additionalCharacters"
					],
					"Value": "ReihanaSBV 39 54 right/AichaSBV 40 54 left",
					"Delimiter": "/",
				},
				// Main Event
				{
					"Operation": "Append",
					"Target": [
						"Entries",
						"Main-Event_additionalCharacters"
					],
					"Value": "ReihanaSBV 39 54 right/AichaSBV 40 54 left",
					"Delimiter": "/",
				},
			]
		},
		// Demons Year 2
		{
			"Action": "EditData",
			"Target": "Data/Festivals/winter8",
			"When": {
				"HasSeenEvent": "{{ModId}}_20031427"
			},
			"TextOperations": [
				// Set-up
				{
					"Operation": "Append",
					"Target": [
						"Entries",
						"Set-Up_additionalCharacters_y2"
					],
					"Value": "ReihanaSBV 53 53 right/AichaSBV 54 53 left",
					"Delimiter": "/",
				},
				// Main Event
				{
					"Operation": "Append",
					"Target": [
						"Entries",
						"Main-Event_additionalCharacters_y2"
					],
					"Value": "ReihanaSBV 53 53 right/AichaSBV 54 53 left",
					"Delimiter": "/",
				},
			]
		},
	]
}