{
	"Changes": [
		{
			"LogName": "Add SBV Locations to Warp Sections",
			"Action": "EditData",
			"Target": "Mods/CJBok.CheatsMenu/WarpSections",
			"Entries": {
				"{{ModId}}_SunberryVillage": {
					"Id": "{{ModId}}_SunberryVillage",
					"DisplayName": "{{i18n:Sunberry.Locations.SunberryVillage}}",
					"Order": 100
				},
				"{{ModId}}_SunberryMountain": {
					"Id": "{{ModId}}_SunberryMountain",
					"DisplayName": "{{i18n:Sunberry.Locations.SunberryMountain}}",
					"Order": 101
				},
				"{{ModId}}_SunberryForest": {
					"Id": "{{ModId}}_SunberryForest",
					"DisplayName": "{{i18n:Sunberry.Locations.SunberryForest}}",
					"Order": 102
				}
			}
		},
		{
			"LogName": "Add Warps to CJB Menu",
			"Action": "EditData",
			"Target": "Mods/CJBok.CheatsMenu/Warps",
			"Entries": {
				// Village
				"{{ModId}}_AriMarket": {
					"Id": "{{ModId}}_AriMarket",
					"SectionId": "{{ModId}}_SunberryVillage",
					"DisplayName": "{{i18n:Sunberry.Locations.AriMarket}}",
					"Location": "Custom_SBV_SunberryVillage",
					"Tile": "88, 51"
				},
				"{{ModId}}_CarPark": {
					"Id": "{{ModId}}_CarPark",
					"SectionId": "{{ModId}}_SunberryVillage",
					"DisplayName": "{{i18n:Sunberry.Locations.CarPark}}",
					"Location": "Custom_SBV_SunberryVillage",
					"Tile": "6, 10"
				},
				"{{ModId}}_DNDCafe": {
					"Id": "{{ModId}}_DNDCafe",
					"SectionId": "{{ModId}}_SunberryVillage",
					"DisplayName": "{{i18n:Sunberry.Locations.DNDCafe}}",
					"Location": "Custom_SBV_SunberryVillage",
					"Tile": "49, 27"
				},
				"{{ModId}}_EzraClothes": {
					"Id": "{{ModId}}_EzraClothes",
					"SectionId": "{{ModId}}_SunberryVillage",
					"DisplayName": "{{i18n:Sunberry.Locations.EzraClothes}}",
					"Location": "Custom_SBV_SunberryVillage",
					"Tile": "49, 15"
				},
				"{{ModId}}_FountainArea": {
					"Id": "{{ModId}}_FountainArea",
					"SectionId": "{{ModId}}_SunberryVillage",
					"DisplayName": "{{i18n:Sunberry.Locations.FountainArea}}",
					"Location": "Custom_SBV_SunberryVillage",
					"Tile": "66, 86"
				},
				"{{ModId}}_JumanaShop": {
					"Id": "{{ModId}}_JumanaShop",
					"SectionId": "{{ModId}}_SunberryVillage",
					"DisplayName": "{{i18n:Sunberry.Locations.MaiaHouse}}",
					"Location": "Custom_SBV_SunberryVillage",
					"Tile": "31, 50"
				},
				"{{ModId}}_SerenityInn": {
					"Id": "{{ModId}}_SerenityInn",
					"SectionId": "{{ModId}}_SunberryVillage",
					"DisplayName": "{{i18n:Sunberry.Locations.SerenityInn}}",
					"Location": "Custom_SBV_SunberryVillage",
					"Tile": "74, 32"
				},
				"{{ModId}}_SunberryLibrary": {
					"Id": "{{ModId}}_SunberryLibrary",
					"SectionId": "{{ModId}}_SunberryVillage",
					"DisplayName": "{{i18n:Sunberry.Locations.SunberryLibrary}}",
					"Location": "Custom_SBV_SunberryVillage",
					"Tile": "73, 14"
				},
				// Mountain
				"{{ModId}}_BrokenDiner": {
					"Id": "{{ModId}}_BrokenDiner",
					"SectionId": "{{ModId}}_SunberryMountain",
					"DisplayName": "{{i18n:Sunberry.Locations.ChrisDinerBroken}}",
					"Location": "Custom_SBV_SunberryMountain",
					"Tile": "28, 19"
				},
				"{{ModId}}_SilasBlacksmith": {
					"Id": "{{ModId}}_SilasBlacksmith",
					"SectionId": "{{ModId}}_SunberryMountain",
					"DisplayName": "{{i18n:Sunberry.Locations.SilasBlacksmith}}",
					"Location": "Custom_SBV_SunberryMountain",
					"Tile": "16, 24"
				},
				"{{ModId}}_SunberryMines": {
					"Id": "{{ModId}}_SunberryMines",
					"SectionId": "{{ModId}}_SunberryMountain",
					"DisplayName": "{{i18n:Sunberry.Locations.CrystalCave}}",
					"Location": "Custom_SBV_CrystalCave",
					"Tile": "10, 14"
				},
				// Forest
				"{{ModId}}_AbandonedHouse": {
					"Id": "{{ModId}}_AbandonedHouse",
					"SectionId": "{{ModId}}_SunberryForest",
					"DisplayName": "{{i18n:Sunberry.Locations.AbandonedHouse}}",
					"Location": "Custom_SBV_SunberryForest",
					"Tile": "54, 14"
				},
				"{{ModId}}_BrokenBarn": {
					"Id": "{{ModId}}_BrokenBarn",
					"SectionId": "{{ModId}}_SunberryForest",
					"DisplayName": "{{i18n:Sunberry.Locations.BrokenBarn}}",
					"Location": "Custom_SBV_SunberryForest",
					"Tile": "13, 49"
				}
			}
		}
	]
}